ipify_me/__init__.py
ipify_me/cli.py
ipify_me/core.py
ipify_me-1.1.0.dist-info/AUTHORS.md
ipify_me-1.1.0.dist-info/LICENSE
ipify_me-1.1.0.dist-info/METADATA
ipify_me-1.1.0.dist-info/WHEEL
ipify_me-1.1.0.dist-info/entry_points.txt
ipify_me-1.1.0.dist-info/top_level.txt
ipify_me-1.1.0.dist-info/RECORD
