Metadata-Version: 2.1
Name: ipify-me
Version: 1.1.0
Summary: Retreive your public IP address using Ipify's free API.
Home-page: https://github.com/infosecb/ipify_me
Author: Brendan Chamberlain
Author-email: brendan@infosecb.com
License: Apache Software License 2.0
Keywords: ipify_me
Platform: UNKNOWN
Classifier: Development Status :: 2 - Pre-Alpha
Classifier: Intended Audience :: Developers
Classifier: License :: OSI Approved :: Apache Software License
Classifier: Natural Language :: English
Classifier: Programming Language :: Python :: 3
Classifier: Programming Language :: Python :: 3.5
Classifier: Programming Language :: Python :: 3.6
Classifier: Programming Language :: Python :: 3.7
Classifier: Programming Language :: Python :: 3.8
Requires-Python: >=3.5
Requires-Dist: Click (>=7.0)
Requires-Dist: requests
